pelican_cite/__init__.py
pelican_cite/templates/citations.html
pelican_cite/templates/label.html
pelican_cite-1.1.1.dist-info/LICENSE
pelican_cite-1.1.1.dist-info/WHEEL
pelican_cite-1.1.1.dist-info/METADATA
pelican_cite-1.1.1.dist-info/RECORD
